netcup_cli/__init__.py
netcup_cli/main.py
netcup_cli/project_manager.py
netcup_cli-0.1.4.dist-info/METADATA
netcup_cli-0.1.4.dist-info/WHEEL
netcup_cli-0.1.4.dist-info/entry_points.txt
netcup_cli-0.1.4.dist-info/top_level.txt
netcup_cli-0.1.4.dist-info/RECORD
