Metadata-Version: 2.4
Name: netcup-cli
Version: 0.1.4
Summary: CLI tool for interacting with the Netcup Webservice
Author: Mihnea-Octavian Manolache
Author-email: me@mihnea.dev
Classifier: Programming Language :: Python :: 3
Classifier: License :: OSI Approved :: MIT License
Classifier: Operating System :: OS Independent
Requires-Python: >=3.6
Requires-Dist: zeep
Requires-Dist: netcup_webservice
Dynamic: author
Dynamic: author-email
Dynamic: classifier
Dynamic: description
Dynamic: description-content-type
Dynamic: requires-dist
Dynamic: requires-python
Dynamic: summary
